LICENSE
README.md
setup.py
damilu_sigma/BCD_tools.py
damilu_sigma/SimClR_tools.py
damilu_sigma/__init__.py
damilu_sigma/logger_damilu.py
damilu_sigma/model_pretrain.py
damilu_sigma.egg-info/PKG-INFO
damilu_sigma.egg-info/SOURCES.txt
damilu_sigma.egg-info/dependency_links.txt
damilu_sigma.egg-info/top_level.txt